buttonpad/__init__.py
buttonpad/__main__.py
buttonpad/calculator.py
buttonpad/connectfour.py
buttonpad/conwaysgameoflife.py
buttonpad/delme_2.py
buttonpad/delmeparlorpuzzle.py
buttonpad/demoenterexit.py
buttonpad/demokeyboardmove.py
buttonpad/demophonekeypad.py
buttonpad/demophonekeypad2.py
buttonpad/dodgerrace.py
buttonpad/eightqueens.py
buttonpad/emojicopypad.py
buttonpad/fishtank.py
buttonpad/floodit.py
buttonpad/gomoku.py
buttonpad/launcher.py
buttonpad/lightsout.py
buttonpad/magic8ball.py
buttonpad/memorypuzzle.py
buttonpad/othello.py
buttonpad/othellovscpu.py
buttonpad/pegsolitaire.py
buttonpad/pixeleditor.py
buttonpad/samegame.py
buttonpad/simon.py
buttonpad/slidepuzzle.py
buttonpad/stopwatch.py
buttonpad/tictactoe.py
buttonpad/tictactoevscpu.py
buttonpad/twentyfortyeight.py
buttonpad-0.4.0.dist-info/METADATA
buttonpad-0.4.0.dist-info/WHEEL
buttonpad-0.4.0.dist-info/top_level.txt
buttonpad-0.4.0.dist-info/RECORD
